{"planes":{"2026-04-20":{"filas":[{"id":"1776460206759-1-0jenc","tanque":"014","producto":"L70","cliente":"UNILEVER DE ARGENTINA S.A","buque":"BHARMO","viaje":"2601","subCliente":"UNILEVER DE ARGENTINA S.A","conoc":"1402","despacho":"DI26IC04002168T","exLegal":"155654","fechaOrig":"16/03/2026","horaCarga":"11:00","observaciones":"","cumplido":false,"salidaId":null,"cumplidoAt":null},{"id":"1776460206759-2-x6su5","tanque":"023","producto":"ED6","cliente":"BRENNTAG ARG.S.A.","buque":"BFORTU","viaje":"2601","subCliente":"BRENNTAG ARG.S.A.","conoc":"S19B","despacho":"DI26IC04002559A","exLegal":"20868","fechaOrig":"31/03/2026","horaCarga":"07:00","observaciones":"","cumplido":false,"salidaId":null,"cumplidoAt":null},{"id":"1776460206759-3-v98i7","tanque":"026","producto":"IPE","cliente":"BRENNTAG ARG.S.A.","buque":"BCHAIN","viaje":"2302","subCliente":"PBBPOLISUR S.R.L.","conoc":"US33","despacho":"DI23IC04009487E","exLegal":"110607","fechaOrig":"11/08/2025","horaCarga":"08:00","observaciones":"","cumplido":false,"salidaId":null,"cumplidoAt":null},{"id":"1776460206759-4-l7br3","tanque":"028","producto":"VOR","cliente":"PBBPOLISUR S.R.L.","buque":"SBISMU","viaje":"2601","subCliente":"PBBPOLISUR S.R.L.","conoc":"0840","despacho":"DI26IC04002235Y","exLegal":"76456","fechaOrig":"18/03/2026","horaCarga":"09:00","observaciones":"","cumplido":false,"salidaId":null,"cumplidoAt":null},{"id":"1776460206759-5-qbyuv","tanque":"028","producto":"VOR","cliente":"PBBPOLISUR S.R.L.","buque":"SBISMU","viaje":"2601","subCliente":"PBBPOLISUR S.R.L.","conoc":"0840","despacho":"DI26IC04002235Y","exLegal":"76456","fechaOrig":"18/03/2026","horaCarga":"09:00","observaciones":"","cumplido":false,"salidaId":null,"cumplidoAt":null},{"id":"1776460206759-6-fxo8s","tanque":"028","producto":"VOR","cliente":"PBBPOLISUR S.R.L.","buque":"SBISMU","viaje":"2601","subCliente":"PBBPOLISUR S.R.L.","conoc":"0840","despacho":"DI26IC04002235Y","exLegal":"76456","fechaOrig":"18/03/2026","horaCarga":"09:00","observaciones":"","cumplido":false,"salidaId":null,"cumplidoAt":null},{"id":"1776460206759-7-6m6zv","tanque":"053","producto":"NRE","cliente":"TRAFIGURA ARGENTINA S.A.","buque":"AYANE","viaje":"2601","subCliente":"TRAFIGURA ARGENTINA S.A.","conoc":"0001","despacho":"2608REMO000110U","exLegal":"73178","fechaOrig":"07/04/2026","horaCarga":"07:00","observaciones":"","cumplido":false,"salidaId":null,"cumplidoAt":null},{"id":"1776460206759-8-2z8wv","tanque":"053","producto":"NRE","cliente":"TRAFIGURA ARGENTINA S.A.","buque":"AYANE","viaje":"2601","subCliente":"TRAFIGURA ARGENTINA S.A.","conoc":"0001","despacho":"2608REMO000110U","exLegal":"73178","fechaOrig":"07/04/2026","horaCarga":"07:00","observaciones":"","cumplido":false,"salidaId":null,"cumplidoAt":null},{"id":"1776460206760-9-yb6nb","tanque":"076","producto":"MDI","cliente":"PBBPOLISUR S.R.L.","buque":"BFORTU","viaje":"2601","subCliente":"PBBPOLISUR S.R.L.","conoc":"S11B","despacho":"DI26IC04002547U","exLegal":"314974","fechaOrig":"31/03/2026","horaCarga":"10:00","observaciones":"","cumplido":false,"salidaId":null,"cumplidoAt":null},{"id":"1776460206760-10-mnbp8","tanque":"076","producto":"MDI","cliente":"PBBPOLISUR S.R.L.","buque":"BFORTU","viaje":"2601","subCliente":"PBBPOLISUR S.R.L.","conoc":"S11B","despacho":"DI26IC04002547U","exLegal":"314974","fechaOrig":"31/03/2026","horaCarga":"10:00","observaciones":"","cumplido":false,"salidaId":null,"cumplidoAt":null},{"id":"1776460206760-11-h51bs","tanque":"088","producto":"PGU","cliente":"PBBPOLISUR S.R.L.","buque":"BHARMO","viaje":"2601","subCliente":"PBBPOLISUR S.R.L.","conoc":"0701","despacho":"DI26IC04002173P","exLegal":"279974","fechaOrig":"16/03/2026","horaCarga":"09:00","observaciones":"","cumplido":false,"salidaId":null,"cumplidoAt":null},{"id":"1776460206760-12-zxb83","tanque":"088","producto":"PGU","cliente":"PBBPOLISUR S.R.L.","buque":"BHARMO","viaje":"2601","subCliente":"PBBPOLISUR S.R.L.","conoc":"0701","despacho":"DI26IC04002173P","exLegal":"279974","fechaOrig":"16/03/2026","horaCarga":"09:00","observaciones":"","cumplido":false,"salidaId":null,"cumplidoAt":null},{"id":"1776460206760-13-imgct","tanque":"088","producto":"PGU","cliente":"PBBPOLISUR S.R.L.","buque":"BHARMO","viaje":"2601","subCliente":"PBBPOLISUR S.R.L.","conoc":"0702","despacho":"DI26TRM6000115U","exLegal":"28000","fechaOrig":"16/04/2026","horaCarga":"08:00","observaciones":"","cumplido":false,"salidaId":null,"cumplidoAt":null}],"asunto":"plan de carga 20/4/2026","filename":"aduana.xls","importadoAt":"2026-04-17T21:10:06.760Z","importadoPor":"julian"},"2026-04-17":{"filas":[{"id":"1776461782529-1-ss5o5","tanque":"014","producto":"UNITOL L-70","cliente":"UNILEVER DE ARGENTINA S.A","buque":"BHARMO","viaje":"2601","subCliente":"UNILEVER DE ARGENTINA S.A","conoc":"1402","despacho":"DI26IC04002168T","exLegal":"155654","fechaOrig":"16/03/2026","horaCarga":"11:00","observaciones":"","cumplido":true,"salidaId":1776432288063,"cumplidoAt":"2026-04-17T21:36:22.530Z"},{"id":"1776461782529-2-7bc5m","tanque":"023","producto":"EXXSOL D-60","cliente":"BRENNTAG ARG.S.A.","buque":"BFORTU","viaje":"2601","subCliente":"BRENNTAG ARG.S.A.","conoc":"S19B","despacho":"DI26IC04002559A","exLegal":"20868","fechaOrig":"31/03/2026","horaCarga":"07:00","observaciones":"","cumplido":false,"salidaId":null,"cumplidoAt":null},{"id":"1776461782529-3-kcize","tanque":"026","producto":"ISOPAR E","cliente":"BRENNTAG ARG.S.A.","buque":"BCHAIN","viaje":"2302","subCliente":"PBBPOLISUR S.R.L.","conoc":"US33","despacho":"DI23IC04009487E","exLegal":"110607","fechaOrig":"11/08/2025","horaCarga":"08:00","observaciones":"","cumplido":false,"salidaId":null,"cumplidoAt":null},{"id":"1776461782529-4-6pio7","tanque":"028","producto":"VORANOL 3011","cliente":"PBBPOLISUR S.R.L.","buque":"SBISMU","viaje":"2601","subCliente":"PBBPOLISUR S.R.L.","conoc":"0840","despacho":"DI26IC04002235Y","exLegal":"76456","fechaOrig":"18/03/2026","horaCarga":"09:00","observaciones":"","cumplido":false,"salidaId":null,"cumplidoAt":null},{"id":"1776461782529-5-3oqob","tanque":"028","producto":"VORANOL 3011","cliente":"PBBPOLISUR S.R.L.","buque":"SBISMU","viaje":"2601","subCliente":"PBBPOLISUR S.R.L.","conoc":"0840","despacho":"DI26IC04002235Y","exLegal":"76456","fechaOrig":"18/03/2026","horaCarga":"09:00","observaciones":"","cumplido":false,"salidaId":null,"cumplidoAt":null},{"id":"1776461782529-6-aa7wf","tanque":"028","producto":"VORANOL 3011","cliente":"PBBPOLISUR S.R.L.","buque":"SBISMU","viaje":"2601","subCliente":"PBBPOLISUR S.R.L.","conoc":"0840","despacho":"DI26IC04002235Y","exLegal":"76456","fechaOrig":"18/03/2026","horaCarga":"09:00","observaciones":"","cumplido":false,"salidaId":null,"cumplidoAt":null},{"id":"1776461782529-7-q2tp0","tanque":"053","producto":"NRE","cliente":"TRAFIGURA ARGENTINA S.A.","buque":"AYANE","viaje":"2601","subCliente":"TRAFIGURA ARGENTINA S.A.","conoc":"0001","despacho":"2608REMO000110U","exLegal":"73178","fechaOrig":"07/04/2026","horaCarga":"07:00","observaciones":"","cumplido":false,"salidaId":null,"cumplidoAt":null},{"id":"1776461782529-8-nuxxs","tanque":"053","producto":"NRE","cliente":"TRAFIGURA ARGENTINA S.A.","buque":"AYANE","viaje":"2601","subCliente":"TRAFIGURA ARGENTINA S.A.","conoc":"0001","despacho":"2608REMO000110U","exLegal":"73178","fechaOrig":"07/04/2026","horaCarga":"07:00","observaciones":"","cumplido":false,"salidaId":null,"cumplidoAt":null},{"id":"1776461782529-9-0ldfm","tanque":"076","producto":"DIFENILMETANO DIISOCIANATO","cliente":"PBBPOLISUR S.R.L.","buque":"BFORTU","viaje":"2601","subCliente":"PBBPOLISUR S.R.L.","conoc":"S11B","despacho":"DI26IC04002547U","exLegal":"314974","fechaOrig":"31/03/2026","horaCarga":"10:00","observaciones":"","cumplido":false,"salidaId":null,"cumplidoAt":null},{"id":"1776461782529-10-gdzql","tanque":"076","producto":"DIFENILMETANO DIISOCIANATO","cliente":"PBBPOLISUR S.R.L.","buque":"BFORTU","viaje":"2601","subCliente":"PBBPOLISUR S.R.L.","conoc":"S11B","despacho":"DI26IC04002547U","exLegal":"314974","fechaOrig":"31/03/2026","horaCarga":"10:00","observaciones":"","cumplido":false,"salidaId":null,"cumplidoAt":null},{"id":"1776461782529-11-dr8dh","tanque":"088","producto":"PROPILENGLICOL USP","cliente":"PBBPOLISUR S.R.L.","buque":"BHARMO","viaje":"2601","subCliente":"PBBPOLISUR S.R.L.","conoc":"0701","despacho":"DI26IC04002173P","exLegal":"279974","fechaOrig":"16/03/2026","horaCarga":"09:00","observaciones":"","cumplido":true,"salidaId":1776425465392,"cumplidoAt":"2026-04-17T21:36:22.530Z"},{"id":"1776461782529-12-ie6wu","tanque":"088","producto":"PROPILENGLICOL USP","cliente":"PBBPOLISUR S.R.L.","buque":"BHARMO","viaje":"2601","subCliente":"PBBPOLISUR S.R.L.","conoc":"0701","despacho":"DI26IC04002173P","exLegal":"279974","fechaOrig":"16/03/2026","horaCarga":"09:00","observaciones":"","cumplido":true,"salidaId":1776422901191,"cumplidoAt":"2026-04-17T21:36:22.530Z"},{"id":"1776461782529-13-r7d2u","tanque":"088","producto":"PROPILENGLICOL USP","cliente":"PBBPOLISUR S.R.L.","buque":"BHARMO","viaje":"2601","subCliente":"PBBPOLISUR S.R.L.","conoc":"0702","despacho":"DI26TRM6000115U","exLegal":"28000","fechaOrig":"16/04/2026","horaCarga":"08:00","observaciones":"","cumplido":false,"salidaId":null,"cumplidoAt":null}],"asunto":"plan de carga 20/4/2026","filename":"aduana.xls","importadoAt":"2026-04-17T21:36:22.529Z","importadoPor":"julian"}},"actualizado":"2026-04-17T21:36:24.039Z"}